comprep/__init__.py
comprep/_comprep_template.zsh
comprep/argparse_completion.py
comprep/comprep.py
comprep-0.2.0.dist-info/WHEEL
comprep-0.2.0.dist-info/METADATA
comprep-0.2.0.dist-info/RECORD
