Metadata-Version: 2.1
Name: comprep
Version: 0.2.0
Summary: 
Author: riku.okajima
Author-email: riku.okajima@gmail.com
Requires-Python: >=3.8,<4.0
Classifier: Programming Language :: Python :: 3
Classifier: Programming Language :: Python :: 3.8
Requires-Dist: colorama (>=0.4.3,<0.5.0)
